mlbi_sers/__init__.py
mlbi_sers/bistack.py
mlbi_sers/load_data.py
mlbi_sers/sers.py
mlbi_sers-0.1.3.dist-info/licenses/LICENSE
sers/__init__.py
sers/sers.py
mlbi_sers-0.1.3.dist-info/METADATA
mlbi_sers-0.1.3.dist-info/WHEEL
mlbi_sers-0.1.3.dist-info/entry_points.txt
mlbi_sers-0.1.3.dist-info/top_level.txt
mlbi_sers-0.1.3.dist-info/RECORD
