Metadata-Version: 2.4
Name: mlbi-sers
Version: 0.1.3
Summary: Tookits for SERS data processing.
Author-email: Seokhyun Yoon <syoon@dku.edu>
License: MIT License
Project-URL: Homepage, https://github.com/combio-dku/
Keywords: SERS,Raman Spectrum
Classifier: Programming Language :: Python
Classifier: Programming Language :: Python :: 3
License-File: LICENSE
Provides-Extra: dev
Requires-Dist: numpy; extra == "dev"
Requires-Dist: pandas; extra == "dev"
Requires-Dist: scipy; extra == "dev"
Requires-Dist: scikit-learn; extra == "dev"
Requires-Dist: scikit-network; extra == "dev"
Requires-Dist: scanpy; extra == "dev"
Requires-Dist: seaborn; extra == "dev"
Dynamic: license-file
